ChineseDB.py
pinyin_utils.py
tabdb.py
translate.py
pinyin_utils-0.3.0.dist-info/METADATA
pinyin_utils-0.3.0.dist-info/WHEEL
pinyin_utils-0.3.0.dist-info/top_level.txt
pinyin_utils-0.3.0.dist-info/RECORD
