Metadata-Version: 2.1
Name: pinyin-utils
Version: 0.3.0
Summary: Utilities for handling Chinese pinyin
Home-page: https://github.com/johndeighan/pinyin_utils
Author: John Deighan
Author-email: john.deighan@gmail.com
License: MIT
Platform: UNKNOWN
Classifier: Programming Language :: Python :: 3
Classifier: License :: OSI Approved :: MIT License
Classifier: Operating System :: OS Independent
Requires-Python: >=3.6
